rpa_finder/ReactionSystem.py
rpa_finder/__init__.py
rpa_finder/linalg.py
rpa_finder/reaction_system.py
rpa_finder/sandbox.py
rpa_finder/utils.py
tests/__init__.py
tests/test_reactionsystem.py
rpa_finder-0.1.2.dist-info/METADATA
rpa_finder-0.1.2.dist-info/WHEEL
rpa_finder-0.1.2.dist-info/top_level.txt
rpa_finder-0.1.2.dist-info/RECORD
