Metadata-Version: 2.1
Name: rpa-finder
Version: 0.1.2
Summary: A python package to find robust perfect adaptation of chemical reaction networks.
Home-page: https://github.com/yhirono/RPAFinder
Author: Yuji Hirono, Ankit Gupta
Author-email: yuji.hirono@gmail.com
License: UNKNOWN
Platform: UNKNOWN
Classifier: Programming Language :: Python :: 3
Classifier: License :: OSI Approved :: MIT License
Classifier: Operating System :: OS Independent
Requires-Dist: numpy (>=1.25.2)
Requires-Dist: python-libsbml (>=5.20.2)
Requires-Dist: scipy (>=1.13.0)
Requires-Dist: setuptools (>=58.0.4)
Requires-Dist: sympy (>=1.12)
Requires-Dist: matplotlib (>=3.8.2)
